[
    {
        "Name": "Ph\u1edf B\u00e0 Tuy\u1ebft",
        "Rating": 4.8,
        "Price": null,
        "Opening Hour": null,
        "Description": "1a D\u01b0\u1eddng Yersin, Ph\u00fa Trinh, Th\u00e0nh ph\u1ed1 Phan Thi\u1ebft, B\u00ecnh Thu\u1eadn, Vietnam, Vietnamese restaurant",
        "Latitude": 10.9313263,
        "Longitude": 108.0968643,
        "Distance (km)": 0.89,
        "session_id": "cc73e928-bed5-4a0a-80ff-3168ddba95da",
        "generatedAt": "2025-03-26T02:41:34.937864"
    },
    {
        "Name": "Ph\u00fa Qu\u00fd Seafood Restaurant",
        "Rating": 4.5,
        "Price": null,
        "Opening Hour": "Open 24 hours",
        "Description": "29-31-33 Ph\u1ea1m V\u0103n \u0110\u1ed3ng, B\u00ecnh H\u01b0ng, Th\u00e0nh ph\u1ed1 Phan Thi\u1ebft, B\u00ecnh Thu\u1eadn, Vietnam, Restaurant",
        "Latitude": 10.925274,
        "Longitude": 108.10363059999999,
        "Distance (km)": 0.4,
        "session_id": "cc73e928-bed5-4a0a-80ff-3168ddba95da",
        "generatedAt": "2025-03-26T02:41:34.937864"
    },
    {
        "Name": "MOJO Cafe - Restaurant",
        "Rating": 4.4,
        "Price": null,
        "Opening Hour": "Open \u22c5 Closes 10\u202fPM",
        "Description": "204 T\u00f4n \u0110\u1ee9c Th\u1eafng, Ph\u00fa Thu\u1ef7, Th\u00e0nh ph\u1ed1 Phan Thi\u1ebft, B\u00ecnh Thu\u1eadn 80000, Vietnam, Restaurant",
        "Latitude": 10.9335916,
        "Longitude": 108.11134009999999,
        "Distance (km)": 1.62,
        "session_id": "cc73e928-bed5-4a0a-80ff-3168ddba95da",
        "generatedAt": "2025-03-26T02:41:34.937864"
    },
    {
        "Name": "Tobi Koi Sushi Phan Thiet",
        "Rating": 4.8,
        "Price": "$",
        "Opening Hour": "Closed \u22c5 Opens 10:30\u202fAM",
        "Description": "249 Th\u1ee7 Khoa Hu\u00e2n, Ph\u00fa Thu\u1ef7, Th\u00e0nh ph\u1ed1 Phan Thi\u1ebft, B\u00ecnh Thu\u1eadn 77000, Vietnam, Japanese restaurant",
        "Latitude": 10.9328548,
        "Longitude": 108.1112181,
        "Distance (km)": 1.55,
        "session_id": "cc73e928-bed5-4a0a-80ff-3168ddba95da",
        "generatedAt": "2025-03-26T02:41:34.937864"
    },
    {
        "Name": "Vegetarian Restaurant Tre",
        "Rating": 4.4,
        "Price": "\u20ab1\u2013100,000",
        "Opening Hour": "Open \u22c5 Closes 2\u202fPM \u22c5 Reopens 4:30\u202fPM",
        "Description": "74 M\u1eadu Th\u00e2n, B\u00ecnh H\u01b0ng, Th\u00e0nh ph\u1ed1 Phan Thi\u1ebft, B\u00ecnh Thu\u1eadn, Vietnam, Vegan restaurant",
        "Latitude": 10.9293479,
        "Longitude": 108.1099081,
        "Distance (km)": 1.21,
        "session_id": "cc73e928-bed5-4a0a-80ff-3168ddba95da",
        "generatedAt": "2025-03-26T02:41:34.937864"
    },
    {
        "Name": "Thu No Restaurant",
        "Rating": 3.9,
        "Price": "$$",
        "Opening Hour": "Open \u22c5 Closes 10\u202fPM",
        "Description": "17 V\u00f5 Th\u1ecb S\u00e1u, B\u00ecnh H\u01b0ng, Th\u00e0nh ph\u1ed1 Phan Thi\u1ebft, B\u00ecnh Thu\u1eadn, Vietnam, Restaurant",
        "Latitude": 10.925871299999999,
        "Longitude": 108.10353789999999,
        "Distance (km)": 0.42,
        "session_id": "cc73e928-bed5-4a0a-80ff-3168ddba95da",
        "generatedAt": "2025-03-26T02:41:34.937864"
    },
    {
        "Name": "Nam Loan Restaurant 82",
        "Rating": 4,
        "Price": null,
        "Opening Hour": "Open 24 hours",
        "Description": "82 Tr\u01b0ng Tr\u1eafc, \u0110\u1ee9c Th\u1eafng, Th\u00e0nh ph\u1ed1 Phan Thi\u1ebft, B\u00ecnh Thu\u1eadn, Vietnam, Seafood restaurant",
        "Latitude": 10.925387899999999,
        "Longitude": 108.1006589,
        "Distance (km)": 0.16,
        "session_id": "cc73e928-bed5-4a0a-80ff-3168ddba95da",
        "generatedAt": "2025-03-26T02:41:34.937864"
    },
    {
        "Name": "Con Lai Restaurant",
        "Rating": 4.9,
        "Price": null,
        "Opening Hour": "Open \u22c5 Closes 10\u202fPM",
        "Description": "D4/61 Khu \u0111\u00f4 th\u1ecb Du L\u1ecbch Bi\u1ec3n, Tp. Phan Thi\u1ebft, B\u00ecnh Thu\u1eadn 800000, Vietnam, Restaurant",
        "Latitude": 10.93126,
        "Longitude": 108.1202826,
        "Distance (km)": 2.34,
        "session_id": "cc73e928-bed5-4a0a-80ff-3168ddba95da",
        "generatedAt": "2025-03-26T02:41:34.937864"
    },
    {
        "Name": "Restaurant Loan Le",
        "Rating": 4.3,
        "Price": null,
        "Opening Hour": "Closes soon \u22c5 10\u202fAM \u22c5 Opens 6\u202fAM Thu",
        "Description": "\u0110\u1ea1i l\u1ed9, \u0110. L\u00ea Du\u1ea9n, Ph\u00fa Trinh, Th\u00e0nh ph\u1ed1 Phan Thi\u1ebft, B\u00ecnh Thu\u1eadn, Vietnam, Restaurant",
        "Latitude": 10.932549,
        "Longitude": 108.1006498,
        "Distance (km)": 0.95,
        "session_id": "cc73e928-bed5-4a0a-80ff-3168ddba95da",
        "generatedAt": "2025-03-26T02:41:34.937864"
    },
    {
        "Name": "Tu Minh Restaurant",
        "Rating": 3.9,
        "Price": null,
        "Opening Hour": "Closed \u22c5 Opens 11\u202fAM",
        "Description": "17 Ph\u1ea1m V\u0103n \u0110\u1ed3ng, B\u00ecnh H\u01b0ng, Th\u00e0nh ph\u1ed1 Phan Thi\u1ebft, B\u00ecnh Thu\u1eadn, Vietnam, Seafood restaurant",
        "Latitude": 10.9253507,
        "Longitude": 108.10337039999999,
        "Distance (km)": 0.38,
        "session_id": "cc73e928-bed5-4a0a-80ff-3168ddba95da",
        "generatedAt": "2025-03-26T02:41:34.937864"
    }
]